typical_circuit/signal_genetator/signal_gen.sv
`timescale 1ns/1ns
module signal_generator(
	input clk,
	input rst_n,
	input [1:0] wave_choise,
	output reg [4:0]wave
	);

	reg [4:0] count;
	always @(posedge clk or negedge rst_n) begin
		if(~rst_n) begin
			count <= 5'b0;
		end
		else begin
            if(wave_choise == 2'b00) begin
                if(count == 5'd19) begin
                    count <= 5'b0;
                end
                else begin
                    count <= count + 1'b1;
                end   
            end
			else begin
				count <= count;
			end
		end
	end

	reg flag;
	always @(posedge clk or negedge rst_n) begin
		if(~rst_n) begin
			wave <= 5'b0;
			flag <= 1'b1;
		end
		else begin
			case(wave_choise)
				2'b00: begin
					if(count == 5'd9) begin
						wave <= 5'd20;
					end
					else if(count >= 5'd19) begin
						wave <= 5'b0;
					end
					else begin
						wave <= wave;
					end
				end

				2'b01: begin
					if(wave >= 5'd20) begin
						wave <= 5'b0;
					end
					else begin
						wave <= wave + 1'b1;
					end
				end

				2'b10: begin
					if(flag == 1'b0) begin
						if(wave >= 5'd20) begin
							flag <= 1'b1;
							wave <= wave - 1'b1;
						end
						else begin
							wave <= wave + 1'b1;
						end
					end
					else begin
						if(wave == 5'b0) begin
							flag <= 1'b0;
							wave <= wave + 1'b1;
						end
						else begin 
							wave <= wave - 1'b1;
						end
					end
				end
				default: wave <= 5'b0;
			endcase
		end
	end
  
endmodule

typical_circuit/signal_genetator/testbench.sv
`timescale 1ns/1ns
module testbench();

	reg clk,rst_n;
	reg [1:0]wave_choise;
	wire [4:0]wave;

	
initial begin
	// $dumpfile("out.vcd");
	// $dumpvars(0,testbench);
	clk = 0;
	rst_n = 0;
    wave_choise = 2'b00;
    #1 rst_n = 1'b1;
end

// clock generation
initial begin 
    clk <= 0;
    forever begin
    #1 clk <= !clk;
    end
end

initial begin
	forever begin
		#100 wave_choise = wave_choise + 1;
	end
end
// always #100 wave_choise = wave_choise + 1'b1;
// always @(posedge clk or negedge rst_n) begin
//     if(~rst_n) begin
//         wave_choise <= 2'b00;
//     end
//     else begin
//         wave_choise <= wave_choise + 1'b1;
//     end
// end



signal_generator dut(
	.clk(clk),
	.rst_n(rst_n),
	.wave_choise(wave_choise),
	.wave(wave)
	);
endmodule

typical_circuit/signal_genetator/out.vcd
$date
	Fri Apr 07 16:50:03 2023
$end
$version
	QuestaSim Version 10.6c
$end
$timescale
	1ns
$end

$scope module testbench $end
$var reg 1 ! clk $end
$var reg 1 " rst_n $end
$var reg 2 # wave_choise [1:0] $end
$var wire 1 $ wave [4] $end
$var wire 1 % wave [3] $end
$var wire 1 & wave [2] $end
$var wire 1 ' wave [1] $end
$var wire 1 ( wave [0] $end

$scope module dut $end
$var wire 1 ) clk $end
$var wire 1 * rst_n $end
$var wire 1 + wave_choise [1] $end
$var wire 1 , wave_choise [0] $end
$var reg 5 - wave [4:0] $end
$var reg 5 . count [4:0] $end
$var reg 1 / flag $end
$upscope $end
$upscope $end
$enddefinitions $end
#0
$dumpvars
0!
0"
b0 #
b0 -
b0 .
1/
0(
0'
0&
0%
0$
0)
0*
0,
0+
$end
#5
1!
1)
#10
0!
0)
#15
1!
1)
#17
1"
1*
#20
0!
0)
#25
1!
1)
b1 .
#30
0!
0)
#35
1!
1)
b10 .
#40
0!
0)
#45
1!
1)
b11 .
#50
0!
0)
#55
1!
1)
b100 .
#60
0!
0)
#65
1!
1)
b101 .
#70
0!
0)
#75
1!
1)
b110 .
#80
0!
0)
#85
1!
1)
b111 .
#90
0!
0)
#95
1!
1)
b1000 .
#100
0!
0)
#105
1!
1)
b1001 .
#110
0!
0)
#115
1!
1)
b1010 .
b10100 -
1&
1$
#120
0!
0)
#125
1!
1)
b1011 .
#130
0!
0)
#135
1!
1)
b1100 .
#140
0!
0)
#145
1!
1)
b1101 .
#150
0!
0)
#155
1!
1)
b1110 .
#160
0!
0)
#165
1!
1)
b1111 .
#170
0!
0)
#175
1!
1)
b10000 .
#180
0!
0)
#185
1!
1)
b10001 .
#190
0!
0)
#195
1!
1)
b10010 .
#200
0!
0)
#205
1!
1)
b10011 .
#210
0!
0)
#215
1!
1)
b0 .
b0 -
0&
0$
#220
0!
0)
#225
1!
1)
b1 .
#230
0!
0)
#235
1!
1)
b10 .
#240
0!
0)
#245
1!
1)
b11 .
#250
0!
0)
#255
1!
1)
b100 .
#260
0!
0)
#265
1!
1)
b101 .
#270
0!
0)
#275
1!
1)
b110 .
#280
0!
0)
#285
1!
1)
b111 .
#290
0!
0)
#295
1!
1)
b1000 .
#300
0!
0)
#305
1!
1)
b1001 .
#310
0!
0)
#315
1!
1)
b1010 .
b10100 -
1&
1$
#320
0!
0)
#325
1!
1)
b1011 .
#330
0!
0)
#335
1!
1)
b1100 .
#340
0!
0)
#345
1!
1)
b1101 .
#350
0!
0)
#355
1!
1)
b1110 .
#360
0!
0)
#365
1!
1)
b1111 .
#370
0!
0)
#375
1!
1)
b10000 .
#380
0!
0)
#385
1!
1)
b10001 .
#390
0!
0)
#395
1!
1)
b10010 .
#400
0!
0)
#405
1!
1)
b10011 .
#410
0!
0)
#415
1!
1)
b0 .
b0 -
0&
0$
#420
0!
0)
#425
1!
1)
b1 .
#430
0!
0)
#435
1!
1)
b10 .
#440
0!
0)
#445
1!
1)
b11 .
#450
0!
0)
#455
1!
1)
b100 .
#460
0!
0)
#465
1!
1)
b101 .
#470
0!
0)
#475
1!
1)
b110 .
#480
0!
0)
#485
1!
1)
b111 .
#490
0!
0)
#495
1!
1)
b1000 .
#500
0!
0)
#505
1!
1)
b1001 .
#510
0!
0)
#515
1!
1)
b1010 .
b10100 -
1&
1$
#520
0!
0)
#525
1!
1)
b1011 .
#530
0!
0)
#535
1!
1)
b1100 .
#540
0!
0)
#545
1!
1)
b1101 .
#550
0!
0)
#555
1!
1)
b1110 .
#560
0!
0)
#565
1!
1)
b1111 .
#570
0!
0)
#575
1!
1)
b10000 .
#580
0!
0)
#585
1!
1)
b10001 .
#590
0!
0)
#595
1!
1)
b10010 .
#600
0!
0)
#605
1!
1)
b10011 .
#610
0!
0)
#615
1!
1)
b0 .
b0 -
0&
0$
#620
0!
0)
#625
1!
1)
b1 .
#630
0!
0)
#635
1!
1)
b10 .
#640
0!
0)
#645
1!
1)
b11 .
#650
0!
0)
#655
1!
1)
b100 .
#660
0!
0)
#665
1!
1)
b101 .
#670
0!
0)
#675
1!
1)
b110 .
#680
0!
0)
#685
1!
1)
b111 .
#690
0!
0)
#695
1!
1)
b1000 .
#700
0!
0)
#705
1!
1)
b1001 .
#710
0!
0)
#715
1!
1)
b1010 .
b10100 -
1&
1$
#720
0!
0)
#725
1!
1)
b1011 .
#730
0!
0)
#735
1!
1)
b1100 .
#740
0!
0)
#745
1!
1)
b1101 .
#750
0!
0)
#755
1!
1)
b1110 .
#760
0!
0)
#765
1!
1)
b1111 .
#770
0!
0)
#775
1!
1)
b10000 .
#780
0!
0)
#785
1!
1)
b10001 .
#790
0!
0)
#795
1!
1)
b10010 .
#800
0!
0)
#805
1!
1)
b10011 .
#810
0!
0)
#815
1!
1)
b0 .
b0 -
0&
0$
#820
0!
0)
#825
1!
1)
b1 .
#830
0!
0)
#835
1!
1)
b10 .
#840
0!
0)
#845
1!
1)
b11 .
#850
0!
0)
#855
1!
1)
b100 .
#860
0!
0)
#865
1!
1)
b101 .
#870
0!
0)
#875
1!
1)
b110 .
#880
0!
0)
#885
1!
1)
b111 .
#890
0!
0)
#895
1!
1)
b1000 .
#900
0!
0)
#905
1!
1)
b1001 .
#910
0!
0)
#915
1!
1)
b1010 .
b10100 -
1&
1$
#920
0!
0)
#925
1!
1)
b1011 .
#930
0!
0)
#935
1!
1)
b1100 .
#940
0!
0)
#945
1!
1)
b1101 .
#950
0!
0)
#955
1!
1)
b1110 .
#960
0!
0)
#965
1!
1)
b1111 .
#970
0!
0)
#975
1!
1)
b10000 .
#980
0!
0)
#985
1!
1)
b10001 .
#990
0!
0)
#995
1!
1)
b10010 .
#1000
0!
0)
#1005
1!
1)
b10011 .
#1010
0!
0)
#1015
1!
1)
b0 .
b0 -
0&
0$
#1020
0!
0)
#1025
1!
1)
b1 .
#1030
0!
0)
#1035
1!
1)
b10 .
#1040
0!
0)
#1045
1!
1)
b11 .
#1050
0!
0)
#1055
1!
1)
b100 .
#1060
0!
0)
#1065
1!
1)
b101 .
#1070
0!
0)
#1075
1!
1)
b110 .
#1080
0!
0)
#1085
1!
1)
b111 .
#1090
0!
0)
#1095
1!
1)
b1000 .
#1100
0!
0)
#1105
1!
1)
b1001 .
#1110
0!
0)
#1115
1!
1)
b1010 .
b10100 -
1&
1$
#1120
0!
0)
#1125
1!
1)
b1011 .
#1130
0!
0)
#1135
1!
1)
b1100 .
#1140
0!
0)
#1145
1!
1)
b1101 .
#1150
0!
0)
#1155
1!
1)
b1110 .
#1160
0!
0)
#1165
1!
1)
b1111 .
#1170
0!
0)
#1175
1!
1)
b10000 .
#1180
0!
0)
#1185
1!
1)
b10001 .
#1190
0!
0)
#1195
1!
1)
b10010 .
#1200
0!
0)
#1205
1!
1)
b10011 .
#1210
0!
0)
#1215
1!
1)
b0 .
b0 -
0&
0$
#1220
0!
0)
#1225
1!
1)
b1 .
#1230
0!
0)
#1235
1!
1)
b10 .
#1240
0!
0)
#1245
1!
1)
b11 .
#1250
0!
0)
#1255
1!
1)
b100 .
#1260
0!
0)
#1265
1!
1)
b101 .
#1270
0!
0)
#1275
1!
1)
b110 .
#1280
0!
0)
#1285
1!
1)
b111 .
#1290
0!
0)
#1295
1!
1)
b1000 .
#1300
0!
0)
#1305
1!
1)
b1001 .
#1310
0!
0)
#1315
1!
1)
b1010 .
b10100 -
1&
1$
#1320
0!
0)
#1325
1!
1)
b1011 .
#1330
0!
0)
#1335
1!
1)
b1100 .
#1340
0!
0)
#1345
1!
1)
b1101 .
#1350
0!
0)
#1355
1!
1)
b1110 .
#1360
0!
0)
#1365
1!
1)
b1111 .
#1370
0!
0)
#1375
1!
1)
b10000 .
#1380
0!
0)
#1385
1!
1)
b10001 .
#1390
0!
0)
#1395
1!
1)
b10010 .
#1400
0!
0)
#1405
1!
1)
b10011 .
#1410
0!
0)
#1415
1!
1)
b0 .
b0 -
0&
0$
#1420
0!
0)
#1425
1!
1)
b1 .
#1430
0!
0)
#1435
1!
1)
b10 .
#1440
0!
0)
#1445
1!
1)
b11 .
#1450
0!
0)
#1455
1!
1)
b100 .
#1460
0!
0)
#1465
1!
1)
b101 .
#1470
0!
0)
#1475
1!
1)
b110 .
#1480
0!
0)
#1485
1!
1)
b111 .
#1490
0!
0)
#1495
1!
1)
b1000 .
#1500
0!
0)
#1505
1!
1)
b1001 .
#1510
0!
0)
#1515
1!
1)
b1010 .
b10100 -
1&
1$
#1520
0!
0)
#1525
1!
1)
b1011 .
#1530
0!
0)
#1535
1!
1)
b1100 .
#1540
0!
0)
#1545
1!
1)
b1101 .
#1550
0!
0)
#1555
1!
1)
b1110 .
#1560
0!
0)
#1565
1!
1)
b1111 .
#1570
0!
0)
#1575
1!
1)
b10000 .
#1580
0!
0)
#1585
1!
1)
b10001 .
#1590
0!
0)
#1595
1!
1)
b10010 .
#1600
0!
0)
#1605
1!
1)
b10011 .
#1610
0!
0)
#1615
1!
1)
b0 .
b0 -
0&
0$
#1617
b1 #
1,
#1620
0!
0)
#1625
1!
1)
b1 -
1(
#1630
0!
0)
#1635
1!
1)
b10 -
0(
1'
#1640
0!
0)
#1645
1!
1)
b11 -
1(
#1650
0!
0)
#1655
1!
1)
b100 -
0(
0'
1&
#1660
0!
0)
#1665
1!
1)
b101 -
1(
#1670
0!
0)
#1675
1!
1)
b110 -
0(
1'
#1680
0!
0)
#1685
1!
1)
b111 -
1(
#1690
0!
0)
#1695
1!
1)
b1000 -
0(
0'
0&
1%
#1700
0!
0)
#1705
1!
1)
b1001 -
1(
#1710
0!
0)
#1715
1!
1)
b1010 -
0(
1'
#1720
0!
0)
#1725
1!
1)
b1011 -
1(
#1730
0!
0)
#1735
1!
1)
b1100 -
0(
0'
1&
#1740
0!
0)
#1745
1!
1)
b1101 -
1(
#1750
0!
0)
#1755
1!
1)
b1110 -
0(
1'
#1760
0!
0)
#1765
1!
1)
b1111 -
1(
#1770
0!
0)
#1775
1!
1)
b10000 -
0(
0'
0&
0%
1$
#1780
0!
0)
#1785
1!
1)
b10001 -
1(
#1790
0!
0)
#1795
1!
1)
b10010 -
0(
1'
#1800
0!
0)
#1805
1!
1)
b10011 -
1(
#1810
0!
0)
#1815
1!
1)
b10100 -
0(
0'
1&
#1820
0!
0)
#1825
1!
1)
b0 -
0&
0$
#1830
0!
0)
#1835
1!
1)
b1 -
1(
#1840
0!
0)
#1845
1!
1)
b10 -
0(
1'
#1850
0!
0)
#1855
1!
1)
b11 -
1(
#1860
0!
0)
#1865
1!
1)
b100 -
0(
0'
1&
#1870
0!
0)
#1875
1!
1)
b101 -
1(
#1880
0!
0)
#1885
1!
1)
b110 -
0(
1'
#1890
0!
0)
#1895
1!
1)
b111 -
1(
#1900
0!
0)
#1905
1!
1)
b1000 -
0(
0'
0&
1%
#1910
0!
0)
#1915
1!
1)
b1001 -
1(
#1920
0!
0)
#1925
1!
1)
b1010 -
0(
1'
#1930
0!
0)
#1935
1!
1)
b1011 -
1(
#1940
0!
0)
#1945
1!
1)
b1100 -
0(
0'
1&
#1950
0!
0)
#1955
1!
1)
b1101 -
1(
#1960
0!
0)
#1965
1!
1)
b1110 -
0(
1'
#1970
0!
0)
#1975
1!
1)
b1111 -
1(
#1980
0!
0)
#1985
1!
1)
b10000 -
0(
0'
0&
0%
1$
#1990
0!
0)
#1995
1!
1)
b10001 -
1(
#2000
0!
0)
#2005
1!
1)
b10010 -
0(
1'
#2010
0!
0)
#2015
1!
1)
b10011 -
1(
#2020
0!
0)
#2025
1!
1)
b10100 -
0(
0'
1&
#2030
0!
0)
#2035
1!
1)
b0 -
0&
0$
#2040
0!
0)
#2045
1!
1)
b1 -
1(
#2050
0!
0)
#2055
1!
1)
b10 -
0(
1'
#2060
0!
0)
#2065
1!
1)
b11 -
1(
#2070
0!
0)
#2075
1!
1)
b100 -
0(
0'
1&
#2080
0!
0)
#2085
1!
1)
b101 -
1(
#2090
0!
0)
#2095
1!
1)
b110 -
0(
1'
#2100
0!
0)
#2105
1!
1)
b111 -
1(
#2110
0!
0)
#2115
1!
1)
b1000 -
0(
0'
0&
1%
#2120
0!
0)
#2125
1!
1)
b1001 -
1(
#2130
0!
0)
#2135
1!
1)
b1010 -
0(
1'
#2140
0!
0)
#2145
1!
1)
b1011 -
1(
#2150
0!
0)
#2155
1!
1)
b1100 -
0(
0'
1&
#2160
0!
0)
#2165
1!
1)
b1101 -
1(
#2170
0!
0)
#2175
1!
1)
b1110 -
0(
1'
#2180
0!
0)
#2185
1!
1)
b1111 -
1(
#2190
0!
0)
#2195
1!
1)
b10000 -
0(
0'
0&
0%
1$
#2200
0!
0)
#2205
1!
1)
b10001 -
1(
#2210
0!
0)
#2215
1!
1)
b10010 -
0(
1'
#2220
0!
0)
#2225
1!
1)
b10011 -
1(
#2230
0!
0)
#2235
1!
1)
b10100 -
0(
0'
1&
#2240
0!
0)
#2245
1!
1)
b0 -
0&
0$
#2250
0!
0)
#2255
1!
1)
b1 -
1(
#2260
0!
0)
#2265
1!
1)
b10 -
0(
1'
#2270
0!
0)
#2275
1!
1)
b11 -
1(
#2280
0!
0)
#2285
1!
1)
b100 -
0(
0'
1&
#2290
0!
0)
#2295
1!
1)
b101 -
1(
#2300
0!
0)
#2305
1!
1)
b110 -
0(
1'
#2310
0!
0)
#2315
1!
1)
b111 -
1(
#2320
0!
0)
#2325
1!
1)
b1000 -
0(
0'
0&
1%
#2330
0!
0)
#2335
1!
1)
b1001 -
1(
#2340
0!
0)
#2345
1!
1)
b1010 -
0(
1'
#2350
0!
0)
#2355
1!
1)
b1011 -
1(
#2360
0!
0)
#2365
1!
1)
b1100 -
0(
0'
1&
#2370
0!
0)
#2375
1!
1)
b1101 -
1(
#2380
0!
0)
#2385
1!
1)
b1110 -
0(
1'
#2390
0!
0)
#2395
1!
1)
b1111 -
1(
#2400
0!
0)
#2405
1!
1)
b10000 -
0(
0'
0&
0%
1$
#2410
0!
0)
#2415
1!
1)
b10001 -
1(
#2417
b10 #
0,
1+
#2420
0!
0)
#2425
1!
1)
b10000 -
0(
#2430
0!
0)
#2435
1!
1)
b1111 -
1(
1'
1&
1%
0$
#2440
0!
0)
#2445
1!
1)
b1110 -
0(
#2450
0!
0)
#2455
1!
1)
b1101 -
1(
0'
#2460
0!
0)
#2465
1!
1)
b1100 -
0(
#2470
0!
0)
#2475
1!
1)
b1011 -
1(
1'
0&
#2480
0!
0)
#2485
1!
1)
b1010 -
0(
#2490
0!
0)
#2495
1!
1)
b1001 -
1(
0'
#2500
0!
0)
#2505
1!
1)
b1000 -
0(
#2510
0!
0)
#2515
1!
1)
b111 -
1(
1'
1&
0%
#2520
0!
0)
#2525
1!
1)
b110 -
0(
#2530
0!
0)
#2535
1!
1)
b101 -
1(
0'
#2540
0!
0)
#2545
1!
1)
b100 -
0(
#2550
0!
0)
#2555
1!
1)
b11 -
1(
1'
0&
#2560
0!
0)
#2565
1!
1)
b10 -
0(
#2570
0!
0)
#2575
1!
1)
b1 -
1(
0'
#2580
0!
0)
#2585
1!
1)
b0 -
0(
#2590
0!
0)
#2595
1!
1)
0/
b1 -
1(
#2600
0!
0)
#2605
1!
1)
b10 -
0(
1'
#2610
0!
0)
#2615
1!
1)
b11 -
1(
#2620
0!
0)
#2625
1!
1)
b100 -
0(
0'
1&
#2630
0!
0)
#2635
1!
1)
b101 -
1(
#2640
0!
0)
#2645
1!
1)
b110 -
0(
1'
#2650
0!
0)
#2655
1!
1)
b111 -
1(
#2660
0!
0)
#2665
1!
1)
b1000 -
0(
0'
0&
1%
#2670
0!
0)
#2675
1!
1)
b1001 -
1(
#2680
0!
0)
#2685
1!
1)
b1010 -
0(
1'
#2690
0!
0)
#2695
1!
1)
b1011 -
1(
#2700
0!
0)
#2705
1!
1)
b1100 -
0(
0'
1&
#2710
0!
0)
#2715
1!
1)
b1101 -
1(
#2720
0!
0)
#2725
1!
1)
b1110 -
0(
1'
#2730
0!
0)
#2735
1!
1)
b1111 -
1(
#2740
0!
0)
#2745
1!
1)
b10000 -
0(
0'
0&
0%
1$
#2750
0!
0)
#2755
1!
1)
b10001 -
1(
#2760
0!
0)
#2765
1!
1)
b10010 -
0(
1'
#2770
0!
0)
#2775
1!
1)
b10011 -
1(
#2780
0!
0)
#2785
1!
1)
b10100 -
0(
0'
1&
#2790
0!
0)
#2795
1!
1)
1/
b10011 -
1(
1'
0&
#2800
0!
0)
#2805
1!
1)
b10010 -
0(
#2810
0!
0)
#2815
1!
1)
b10001 -
1(
0'
#2820
0!
0)
#2825
1!
1)
b10000 -
0(
#2830
0!
0)
#2835
1!
1)
b1111 -
1(
1'
1&
1%
0$
#2840
0!
0)
#2845
1!
1)
b1110 -
0(
#2850
0!
0)
#2855
1!
1)
b1101 -
1(
0'
#2860
0!
0)
#2865
1!
1)
b1100 -
0(
#2870
0!
0)
#2875
1!
1)
b1011 -
1(
1'
0&
#2880
0!
0)
#2885
1!
1)
b1010 -
0(
#2890
0!
0)
#2895
1!
1)
b1001 -
1(
0'
#2900
0!
0)
#2905
1!
1)
b1000 -
0(
#2910
0!
0)
#2915
1!
1)
b111 -
1(
1'
1&
0%
#2920
0!
0)
#2925
1!
1)
b110 -
0(
#2930
0!
0)
#2935
1!
1)
b101 -
1(
0'
#2940
0!
0)
#2945
1!
1)
b100 -
0(
#2950
0!
0)
#2955
1!
1)
b11 -
1(
1'
0&
#2960
0!
0)
#2965
1!
1)
b10 -
0(
#2970
0!
0)
#2975
1!
1)
b1 -
1(
0'
#2980
0!
0)
#2985
1!
1)
b0 -
0(
#2990
0!
0)
#2995
1!
1)
0/
b1 -
1(
#3000
0!
0)
#3005
1!
1)
b10 -
0(
1'
#3010
0!
0)
#3015
1!
1)
b11 -
1(
#3020
0!
0)
#3025
1!
1)
b100 -
0(
0'
1&
#3030
0!
0)
#3035
1!
1)
b101 -
1(
#3040
0!
0)
#3045
1!
1)
b110 -
0(
1'
#3050
0!
0)
#3055
1!
1)
b111 -
1(
#3060
0!
0)
#3065
1!
1)
b1000 -
0(
0'
0&
1%
#3070
0!
0)
#3075
1!
1)
b1001 -
1(
#3080
0!
0)
#3085
1!
1)
b1010 -
0(
1'
#3090
0!
0)
#3095
1!
1)
b1011 -
1(
#3100
0!
0)
#3105
1!
1)
b1100 -
0(
0'
1&
#3110
0!
0)
#3115
1!
1)
b1101 -
1(
#3120
0!
0)
#3125
1!
1)
b1110 -
0(
1'
#3130
0!
0)
#3135
1!
1)
b1111 -
1(
#3140
0!
0)
#3145
1!
1)
b10000 -
0(
0'
0&
0%
1$
#3150
0!
0)
#3155
1!
1)
b10001 -
1(
#3160
0!
0)
#3165
1!
1)
b10010 -
0(
1'
#3170
0!
0)
#3175
1!
1)
b10011 -
1(
#3180
0!
0)
#3185
1!
1)
b10100 -
0(
0'
1&
#3190
0!
0)
#3195
1!
1)
1/
b10011 -
1(
1'
0&
#3200
0!
0)
#3205
1!
1)
b10010 -
0(
#3210
0!
0)
#3215
1!
1)
b10001 -
1(
0'
#3217
b0 #
0+
#3220
0!
0)
#3225
1!
1)
b1 .
#3230
0!
0)
#3235
1!
1)
b10 .
#3240
0!
0)
#3245
1!
1)
b11 .
#3250
0!
0)
#3255
1!
1)
b100 .
#3260
0!
0)
#3265
1!
1)
b101 .
#3270
0!
0)
#3275
1!
1)
b110 .
#3280
0!
0)
#3285
1!
1)
b111 .
#3290
0!
0)
#3295
1!
1)
b1000 .
#3300
0!
0)
#3305
1!
1)
b1001 .
#3310
0!
0)
#3315
1!
1)
b1010 .
b10100 -
0(
1&
#3320
0!
0)
#3325
1!
1)
b1011 .
#3330
0!
0)
#3335
1!
1)
b1100 .
#3340
0!
0)
#3345
1!
1)
b1101 .
#3350
0!
0)
#3355
1!
1)
b1110 .
#3360
0!
0)
#3365
1!
1)
b1111 .
#3370
0!
0)
#3375
1!
1)
b10000 .
#3380
0!
0)
#3385
1!
1)
b10001 .
#3390
0!
0)
#3395
1!
1)
b10010 .
#3400
0!
0)
#3405
1!
1)
b10011 .
#3410
0!
0)
#3415
1!
1)
b0 .
b0 -
0&
0$
#3420
0!
0)
#3425
1!
1)
b1 .
#3430
0!
0)
#3435
1!
1)
b10 .
#3440
0!
0)
#3445
1!
1)
b11 .
#3450
0!
0)
#3455
1!
1)
b100 .
#3460
0!
0)
#3465
1!
1)
b101 .
#3470
0!
0)
#3475
1!
1)
b110 .
#3480
0!
0)
#3485
1!
1)
b111 .
#3490
0!
0)
#3495
1!
1)
b1000 .
#3500
0!
0)
#3505
1!
1)
b1001 .
#3510
0!
0)
#3515
1!
1)
b1010 .
b10100 -
1&
1$
#3520
0!
0)
#3525
1!
1)
b1011 .
#3530
0!
0)
#3535
1!
1)
b1100 .
#3540
0!
0)
#3545
1!
1)
b1101 .
#3550
0!
0)
#3555
1!
1)
b1110 .
#3560
0!
0)
#3565
1!
1)
b1111 .
#3570
0!
0)
#3575
1!
1)
b10000 .
#3580
0!
0)
#3585
1!
1)
b10001 .
#3590
0!
0)
#3595
1!
1)
b10010 .
#3600
0!
0)
#3605
1!
1)
b10011 .
#3610
0!
0)
#3615
1!
1)
b0 .
b0 -
0&
0$
#3620
0!
0)
#3625
1!
1)
b1 .
#3630
0!
0)
#3635
1!
1)
b10 .
#3640
0!
0)
#3645
1!
1)
b11 .
#3650
0!
0)
#3655
1!
1)
b100 .
#3660
0!
0)
#3665
1!
1)
b101 .
#3670
0!
0)
#3675
1!
1)
b110 .
#3680
0!
0)
#3685
1!
1)
b111 .
#3690
0!
0)
#3695
1!
1)
b1000 .
#3700
0!
0)
#3705
1!
1)
b1001 .
#3710
0!
0)
#3715
1!
1)
b1010 .
b10100 -
1&
1$
#3720
0!
0)
#3725
1!
1)
b1011 .
#3730
0!
0)
#3735
1!
1)
b1100 .
#3740
0!
0)
#3745
1!
1)
b1101 .
#3750
0!
0)
#3755
1!
1)
b1110 .
#3760
0!
0)
#3765
1!
1)
b1111 .
#3770
0!
0)
#3775
1!
1)
b10000 .
#3780
0!
0)
#3785
1!
1)
b10001 .
#3790
0!
0)
#3795
1!
1)
b10010 .
#3800
0!
0)
#3805
1!
1)
b10011 .
#3810
0!
0)
#3815
1!
1)
b0 .
b0 -
0&
0$
#3820
0!
0)
#3825
1!
1)
b1 .
#3830
0!
0)
#3835
1!
1)
b10 .
#3840
0!
0)
#3845
1!
1)
b11 .
#3850
0!
0)
#3855
1!
1)
b100 .
#3860
0!
0)
#3865
1!
1)
b101 .
#3870
0!
0)
#3875
1!
1)
b110 .
#3880
0!
0)
#3885
1!
1)
b111 .
#3890
0!
0)
#3895
1!
1)
b1000 .
#3900
0!
0)
#3905
1!
1)
b1001 .
#3910
0!
0)
#3915
1!
1)
b1010 .
b10100 -
1&
1$
#3920
0!
0)
#3925
1!
1)
b1011 .
#3930
0!
0)
#3935
1!
1)
b1100 .
#3940
0!
0)
#3945
1!
1)
b1101 .
#3950
0!
0)
#3955
1!
1)
b1110 .
#3960
0!
0)
#3965
1!
1)
b1111 .
#3970
0!
0)
#3975
1!
1)
b10000 .
#3980
0!
0)
#3985
1!
1)
b10001 .
#3990
0!
0)
#3995
1!
1)
b10010 .
#4000
0!
0)
#4005
1!
1)
b10011 .
#4010
0!
0)
#4015
1!
1)
b0 .
b0 -
0&
0$
